Workbook

Sheet sku_cost_table_outbound x 100
A1: product_name | B1: node_name | C1: price_sales_shipped | D1: cost_total | E1: profit | F1: marketing_promotion | G1: sales_admin_cost | H1: SGA_total | I1: logistics_costs | J1: warehouse_cost | K1: direct_materials_costs | L1: purchase_total_cost | M1: prod_indirect_labor | N1: prod_indirect_others | O1: direct_labor_costs | P1: depreciation_others | Q1: manufacturing_overhead
A2: CAL_RICE_1 | B2: supply_point | C2: =100*'sku_cost_table_outbound_BK2 (2)'!C2 -> 100 | D2: =100*'sku_cost_table_outbound_BK2 (2)'!D2 -> 99 | E2: =100*'sku_cost_table_outbound_BK2 (2)'!E2 -> 1 | F2: =100*'sku_cost_table_outbound_BK2 (2)'!F2 -> 0 | G2: =100*'sku_cost_table_outbound_BK2 (2)'!G2 -> 1.5 | H2: =100*'sku_cost_table_outbound_BK2 (2)'!H2 -> 1.5 | I2: =100*'sku_cost_table_outbound_BK2 (2)'!I2 -> 1.5 | J2: =100*'sku_cost_table_outbound_BK2 (2)'!J2 -> 0 | ... P2: =100*'sku_cost_table_outbound_BK2 (2)'!P2 -> 0 | Q2: 0.01
A3: CAL_RICE_1 | B3: WS1CAL | C3: =100*'sku_cost_table_outbound_BK2 (2)'!C3 -> 100 | D3: =100*'sku_cost_table_outbound_BK2 (2)'!D3 -> 97.5 | E3: =100*'sku_cost_table_outbound_BK2 (2)'!E3 -> 2.5 | F3: =100*'sku_cost_table_outbound_BK2 (2)'!F3 -> 0 | G3: =100*'sku_cost_table_outbound_BK2 (2)'!G3 -> 4 | H3: =100*'sku_cost_table_outbound_BK2 (2)'!H3 -> 4 | I3: =100*'sku_cost_table_outbound_BK2 (2)'!I3 -> 5 | J3: =100*'sku_cost_table_outbound_BK2 (2)'!J3 -> 8 | ... P3: =100*'sku_cost_table_outbound_BK2 (2)'!P3 -> 0 | Q3: 0.05
A4: CAL_RICE_1 | B4: WS2CAL | C4: =100*'sku_cost_table_outbound_BK2 (2)'!C4 -> 100 | D4: =100*'sku_cost_table_outbound_BK2 (2)'!D4 -> 93.4 | E4: =100*'sku_cost_table_outbound_BK2 (2)'!E4 -> 6.6 | F4: =100*'sku_cost_table_outbound_BK2 (2)'!F4 -> 0 | G4: =100*'sku_cost_table_outbound_BK2 (2)'!G4 -> 8 | H4: =100*'sku_cost_table_outbound_BK2 (2)'!H4 -> 8 | I4: =100*'sku_cost_table_outbound_BK2 (2)'!I4 -> 5 | J4: =100*'sku_cost_table_outbound_BK2 (2)'!J4 -> 0 | ... P4: =100*'sku_cost_table_outbound_BK2 (2)'!P4 -> 0 | Q4: 0.15
A5: CAL_RICE_1 | B5: RT_CAL | C5: =100*'sku_cost_table_outbound_BK2 (2)'!C5 -> 100 | D5: =100*'sku_cost_table_outbound_BK2 (2)'!D5 -> 99.5 | E5: =100*'sku_cost_table_outbound_BK2 (2)'!E5 -> 5 | F5: =100*'sku_cost_table_outbound_BK2 (2)'!F5 -> 0 | G5: =100*'sku_cost_table_outbound_BK2 (2)'!G5 -> 1 | H5: =100*'sku_cost_table_outbound_BK2 (2)'!H5 -> 1 | I5: =100*'sku_cost_table_outbound_BK2 (2)'!I5 -> 0.5 | J5: =100*'sku_cost_table_outbound_BK2 (2)'!J5 -> 0 | ... P5: =100*'sku_cost_table_outbound_BK2 (2)'!P5 -> 0 | Q5: 0
A6: CAL_RICE_1 | B6: CS_CAL | C6: =100*'sku_cost_table_outbound_BK2 (2)'!C6 -> 100 | D6: =100*'sku_cost_table_outbound_BK2 (2)'!D6 -> 100 | E6: =100*'sku_cost_table_outbound_BK2 (2)'!E6 -> 0 | F6: =100*'sku_cost_table_outbound_BK2 (2)'!F6 -> 0 | G6: =100*'sku_cost_table_outbound_BK2 (2)'!G6 -> 0 | H6: =100*'sku_cost_table_outbound_BK2 (2)'!H6 -> 0 | I6: =100*'sku_cost_table_outbound_BK2 (2)'!I6 -> 10 | J6: =100*'sku_cost_table_outbound_BK2 (2)'!J6 -> 0 | ... P6: =100*'sku_cost_table_outbound_BK2 (2)'!P6 -> 0 | Q6: 0
A7: CAL_RICE_1 | B7: DADCAL | C7: =100*'sku_cost_table_outbound_BK2 (2)'!C7 -> 100 | D7: =100*'sku_cost_table_outbound_BK2 (2)'!D7 -> 99 | E7: =100*'sku_cost_table_outbound_BK2 (2)'!E7 -> 1 | F7: =100*'sku_cost_table_outbound_BK2 (2)'!F7 -> 0 | G7: =100*'sku_cost_table_outbound_BK2 (2)'!G7 -> 1.5 | H7: =100*'sku_cost_table_outbound_BK2 (2)'!H7 -> 1.5 | I7: =100*'sku_cost_table_outbound_BK2 (2)'!I7 -> 1.5 | J7: =100*'sku_cost_table_outbound_BK2 (2)'!J7 -> 0 | ... P7: =100*'sku_cost_table_outbound_BK2 (2)'!P7 -> 0 | Q7: 0.01
A8: JPN_Koshihikari | B8: WS1Kosihikari | C8: =100*'sku_cost_table_outbound_BK2 (2)'!C8 -> 100 | D8: =100*'sku_cost_table_outbound_BK2 (2)'!D8 -> 97.5 | E8: =100*'sku_cost_table_outbound_BK2 (2)'!E8 -> 2.5 | F8: =100*'sku_cost_table_outbound_BK2 (2)'!F8 -> 0 | G8: =100*'sku_cost_table_outbound_BK2 (2)'!G8 -> 4 | H8: =100*'sku_cost_table_outbound_BK2 (2)'!H8 -> 4 | I8: =100*'sku_cost_table_outbound_BK2 (2)'!I8 -> 5 | J8: =100*'sku_cost_table_outbound_BK2 (2)'!J8 -> 8 | ... P8: =100*'sku_cost_table_outbound_BK2 (2)'!P8 -> 0 | Q8: 0.05
A9: JPN_Koshihikari | B9: WS2JPN | C9: =100*'sku_cost_table_outbound_BK2 (2)'!C9 -> 100 | D9: =100*'sku_cost_table_outbound_BK2 (2)'!D9 -> 93.4 | E9: =100*'sku_cost_table_outbound_BK2 (2)'!E9 -> 6.6 | F9: =100*'sku_cost_table_outbound_BK2 (2)'!F9 -> 0 | G9: =100*'sku_cost_table_outbound_BK2 (2)'!G9 -> 8 | H9: =100*'sku_cost_table_outbound_BK2 (2)'!H9 -> 8 | I9: =100*'sku_cost_table_outbound_BK2 (2)'!I9 -> 5 | J9: =100*'sku_cost_table_outbound_BK2 (2)'!J9 -> 0 | ... P9: =100*'sku_cost_table_outbound_BK2 (2)'!P9 -> 0 | Q9: 0.15
A10: JPN_Koshihikari | B10: RT_JPN | C10: =100*'sku_cost_table_outbound_BK2 (2)'!C10 -> 100 | D10: =100*'sku_cost_table_outbound_BK2 (2)'!D10 -> 99.5 | E10: =100*'sku_cost_table_outbound_BK2 (2)'!E10 -> 5 | F10: =100*'sku_cost_table_outbound_BK2 (2)'!F10 -> 0 | G10: =100*'sku_cost_table_outbound_BK2 (2)'!G10 -> 1 | H10: =100*'sku_cost_table_outbound_BK2 (2)'!H10 -> 1 | I10: =100*'sku_cost_table_outbound_BK2 (2)'!I10 -> 0.5 | J10: =100*'sku_cost_table_outbound_BK2 (2)'!J10 -> 0 | ... P10: =100*'sku_cost_table_outbound_BK2 (2)'!P10 -> 0 | Q10: 0
A11: JPN_Koshihikari | B11: CS_JPN | C11: =100*'sku_cost_table_outbound_BK2 (2)'!C11 -> 100 | D11: =100*'sku_cost_table_outbound_BK2 (2)'!D11 -> 100 | E11: =100*'sku_cost_table_outbound_BK2 (2)'!E11 -> 0 | F11: =100*'sku_cost_table_outbound_BK2 (2)'!F11 -> 0 | G11: =100*'sku_cost_table_outbound_BK2 (2)'!G11 -> 0 | H11: =100*'sku_cost_table_outbound_BK2 (2)'!H11 -> 0 | I11: =100*'sku_cost_table_outbound_BK2 (2)'!I11 -> 10 | J11: =100*'sku_cost_table_outbound_BK2 (2)'!J11 -> 0 | ... P11: =100*'sku_cost_table_outbound_BK2 (2)'!P11 -> 0 | Q11: 0
A12: JPN_Koshihikari | B12: DADKosihikari | C12: =100*'sku_cost_table_outbound_BK2 (2)'!C12 -> 100 | D12: =100*'sku_cost_table_outbound_BK2 (2)'!D12 -> 99 | E12: =100*'sku_cost_table_outbound_BK2 (2)'!E12 -> 1 | F12: =100*'sku_cost_table_outbound_BK2 (2)'!F12 -> 0 | G12: =100*'sku_cost_table_outbound_BK2 (2)'!G12 -> 1.5 | H12: =100*'sku_cost_table_outbound_BK2 (2)'!H12 -> 1.5 | I12: =100*'sku_cost_table_outbound_BK2 (2)'!I12 -> 1.5 | J12: =100*'sku_cost_table_outbound_BK2 (2)'!J12 -> 0 | ... P12: =100*'sku_cost_table_outbound_BK2 (2)'!P12 -> 0 | Q12: 0.01
A13: JPN_Koshihikari | B13: supply_point | C13: =100*'sku_cost_table_outbound_BK2 (2)'!C13 -> 100 | D13: =100*'sku_cost_table_outbound_BK2 (2)'!D13 -> 99 | E13: =100*'sku_cost_table_outbound_BK2 (2)'!E13 -> 1 | F13: =100*'sku_cost_table_outbound_BK2 (2)'!F13 -> 0 | G13: =100*'sku_cost_table_outbound_BK2 (2)'!G13 -> 1.5 | H13: =100*'sku_cost_table_outbound_BK2 (2)'!H13 -> 1.5 | I13: =100*'sku_cost_table_outbound_BK2 (2)'!I13 -> 1.5 | J13: =100*'sku_cost_table_outbound_BK2 (2)'!J13 -> 0 | ... P13: =100*'sku_cost_table_outbound_BK2 (2)'!P13 -> 0 | Q13: 0.01
... A27: Reserv_Rice | B27: supply_point | C27: =100*'sku_cost_table_outbound_BK2 (2)'!C27 -> 100 | D27: =100*'sku_cost_table_outbound_BK2 (2)'!D27 -> 99 | E27: =100*'sku_cost_table_outbound_BK2 (2)'!E27 -> 1 | F27: =100*'sku_cost_table_outbound_BK2 (2)'!F27 -> 0 | G27: =100*'sku_cost_table_outbound_BK2 (2)'!G27 -> 1.5 | H27: =100*'sku_cost_table_outbound_BK2 (2)'!H27 -> 1.5 | I27: =100*'sku_cost_table_outbound_BK2 (2)'!I27 -> 1.5 | J27: =100*'sku_cost_table_outbound_BK2 (2)'!J27 -> 0 | ... P27: =100*'sku_cost_table_outbound_BK2 (2)'!P27 -> 0 | Q27: 0.01

Sheet sku_cost_table_outbound_BK2 (2)
A1: product_name | B1: node_name | C1: price_sales_shipped | D1: cost_total | E1: profit | F1: marketing_promotion | G1: sales_admin_cost | H1: SGA_total | I1: logistics_costs | J1: warehouse_cost | K1: direct_materials_costs | L1: purchase_total_cost | M1: prod_indirect_labor | N1: prod_indirect_others | O1: direct_labor_costs | P1: depreciation_others | Q1: manufacturing_overhead
A2: CAL_RICE_1 | B2: supply_point | C2: 1 | D2: 0.99 | E2: 0.01 | F2: 0 | G2: 0.015 | H2: 0.015 | I2: 0.015 | J2: 0 | K2: 0.945 | L2: 0.96 | M2: 0 | N2: 0 | O2: 0.01 | P2: 0 | Q2: 0.01
A3: CAL_RICE_1 | B3: WS1CAL | C3: 1 | D3: 0.975 | E3: 0.025 | F3: 0 | G3: 0.04 | H3: 0.04 | I3: 0.05 | J3: 0.08 | K3: 0.745 | L3: 0.875 | M3: 0 | N3: 0 | O3: 0.05 | P3: 0 | Q3: 0.05
A4: CAL_RICE_1 | B4: WS2CAL | C4: 1 | D4: 0.934 | E4: 0.066 | F4: 0 | G4: 0.08 | H4: 0.08 | I4: 0.05 | J4: 0 | K4: 0.634 | L4: 0.684 | M4: 0 | N4: 0 | O4: 0.15 | P4: 0 | Q4: 0.15
A5: CAL_RICE_1 | B5: RT_CAL | C5: 1 | D5: 0.995 | E5: 0.05 | F5: 0 | G5: 0.01 | H5: 0.01 | I5: 0.005 | J5: 0 | K5: 0.972 | L5: 0.977 | M5: 0 | N5: 0 | O5: 0 | P5: 0 | Q5: 0
A6: CAL_RICE_1 | B6: CS_CAL | C6: 1 | D6: 1 | E6: 0 | F6: 0 | G6: 0 | H6: 0 | I6: 0.1 | J6: 0 | K6: 0.9 | L6: 1 | M6: 0 | N6: 0 | O6: 0 | P6: 0 | Q6: 0
A7: CAL_RICE_1 | B7: DADCAL | C7: 1 | D7: 0.99 | E7: 0.01 | F7: 0 | G7: 0.015 | H7: 0.015 | I7: 0.015 | J7: 0 | K7: 0.945 | L7: 0.96 | M7: 0 | N7: 0 | O7: 0.01 | P7: 0 | Q7: 0.01
A8: JPN_Koshihikari | B8: WS1Kosihikari | C8: 1 | D8: 0.975 | E8: 0.025 | F8: 0 | G8: 0.04 | H8: 0.04 | I8: 0.05 | J8: 0.08 | K8: 0.745 | L8: 0.875 | M8: 0 | N8: 0 | O8: 0.05 | P8: 0 | Q8: 0.05
A9: JPN_Koshihikari | B9: WS2JPN | C9: 1 | D9: 0.934 | E9: 0.066 | F9: 0 | G9: 0.08 | H9: 0.08 | I9: 0.05 | J9: 0 | K9: 0.634 | L9: 0.684 | M9: 0 | N9: 0 | O9: 0.15 | P9: 0 | Q9: 0.15
A10: JPN_Koshihikari | B10: RT_JPN | C10: 1 | D10: 0.995 | E10: 0.05 | F10: 0 | G10: 0.01 | H10: 0.01 | I10: 0.005 | J10: 0 | K10: 0.972 | L10: 0.977 | M10: 0 | N10: 0 | O10: 0 | P10: 0 | Q10: 0
A11: JPN_Koshihikari | B11: CS_JPN | C11: 1 | D11: 1 | E11: 0 | F11: 0 | G11: 0 | H11: 0 | I11: 0.1 | J11: 0 | K11: 0.9 | L11: 1 | M11: 0 | N11: 0 | O11: 0 | P11: 0 | Q11: 0
A12: JPN_Koshihikari | B12: DADKosihikari | C12: 1 | D12: 0.99 | E12: 0.01 | F12: 0 | G12: 0.015 | H12: 0.015 | I12: 0.015 | J12: 0 | K12: 0.945 | L12: 0.96 | M12: 0 | N12: 0 | O12: 0.01 | P12: 0 | Q12: 0.01
A13: JPN_Koshihikari | B13: supply_point | C13: 1 | D13: 0.99 | E13: 0.01 | F13: 0 | G13: 0.015 | H13: 0.015 | I13: 0.015 | J13: 0 | K13: 0.945 | L13: 0.96 | M13: 0 | N13: 0 | O13: 0.01 | P13: 0 | Q13: 0.01
... A27: Reserv_Rice | B27: supply_point | C27: 1 | D27: 0.99 | E27: 0.01 | F27: 0 | G27: 0.015 | H27: 0.015 | I27: 0.015 | J27: 0 | K27: 0.945 | L27: 0.96 | M27: 0 | N27: 0 | O27: 0.01 | P27: 0 | Q27: 0.01
