Workbook

Sheet sku_cost_table_inbound x 100
A1: product_name | B1: node_name | C1: price_sales_shipped | D1: cost_total | E1: profit | F1: marketing_promotion | G1: sales_admin_cost | H1: SGA_total | I1: logistics_costs | J1: warehouse_cost | K1: direct_materials_costs | L1: tariff_cost | M1: purchase_total_cost | N1: prod_indirect_labor | O1: prod_indirect_others | P1: direct_labor_costs | Q1: depreciation_others | R1: manufacturing_overhead
A2: CAL_RICE_1 | B2: MOMCAL | C2: =100*'sku_cost_table_inbound_BK25 (2)'!C2 -> 100 | D2: =100*'sku_cost_table_inbound_BK25 (2)'!D2 -> 95 | E2: =100*'sku_cost_table_inbound_BK25 (2)'!E2 -> 5 | F2: =100*'sku_cost_table_inbound_BK25 (2)'!F2 -> 0 | G2: =100*'sku_cost_table_inbound_BK25 (2)'!G2 -> 10 | H2: =100*'sku_cost_table_inbound_BK25 (2)'!H2 -> 10 | I2: =100*'sku_cost_table_inbound_BK25 (2)'!I2 -> 5 | J2: =100*'sku_cost_table_inbound_BK25 (2)'!J2 -> 0 | K2: =100*'sku_cost_table_inbound_BK25 (2)'!K2 -> 30 | L2: 0 | M2: =100*'sku_cost_table_inbound_BK25 (2)'!M2 -> 35 | N2: =100*'sku_cost_table_inbound_BK25 (2)'!N2 -> 3 | O2: =100*'sku_cost_table_inbound_BK25 (2)'!O2 -> 0 | P2: =100*'sku_cost_table_inbound_BK25 (2)'!P2 -> 27 | Q2: =100*'sku_cost_table_inbound_BK25 (2)'!Q2 -> 15 | R2: =100*'sku_cost_table_inbound_BK25 (2)'!R2 -> 45
A3: CAL_RICE_1 | B3: PADCAL | C3: =100*'sku_cost_table_inbound_BK25 (2)'!C3 -> 100 | D3: =100*'sku_cost_table_inbound_BK25 (2)'!D3 -> 95 | E3: =100*'sku_cost_table_inbound_BK25 (2)'!E3 -> 5 | F3: =100*'sku_cost_table_inbound_BK25 (2)'!F3 -> 0 | G3: =100*'sku_cost_table_inbound_BK25 (2)'!G3 -> 10 | H3: =100*'sku_cost_table_inbound_BK25 (2)'!H3 -> 10 | I3: =100*'sku_cost_table_inbound_BK25 (2)'!I3 -> 5 | J3: =100*'sku_cost_table_inbound_BK25 (2)'!J3 -> 0 | K3: =100*'sku_cost_table_inbound_BK25 (2)'!K3 -> 30 | L3: 0 | M3: =100*'sku_cost_table_inbound_BK25 (2)'!M3 -> 35 | N3: =100*'sku_cost_table_inbound_BK25 (2)'!N3 -> 3 | O3: =100*'sku_cost_table_inbound_BK25 (2)'!O3 -> 0 | P3: =100*'sku_cost_table_inbound_BK25 (2)'!P3 -> 27 | Q3: =100*'sku_cost_table_inbound_BK25 (2)'!Q3 -> 15 | R3: =100*'sku_cost_table_inbound_BK25 (2)'!R3 -> 45
A4: JPN_RICE_1 | B4: MOMJPN | C4: =100*'sku_cost_table_inbound_BK25 (2)'!C4 -> 100 | D4: =100*'sku_cost_table_inbound_BK25 (2)'!D4 -> 95 | E4: =100*'sku_cost_table_inbound_BK25 (2)'!E4 -> 5 | F4: =100*'sku_cost_table_inbound_BK25 (2)'!F4 -> 0 | G4: =100*'sku_cost_table_inbound_BK25 (2)'!G4 -> 10 | H4: =100*'sku_cost_table_inbound_BK25 (2)'!H4 -> 10 | I4: =100*'sku_cost_table_inbound_BK25 (2)'!I4 -> 5 | J4: =100*'sku_cost_table_inbound_BK25 (2)'!J4 -> 0 | K4: =100*'sku_cost_table_inbound_BK25 (2)'!K4 -> 30 | L4: 0 | M4: =100*'sku_cost_table_inbound_BK25 (2)'!M4 -> 35 | N4: =100*'sku_cost_table_inbound_BK25 (2)'!N4 -> 3 | O4: =100*'sku_cost_table_inbound_BK25 (2)'!O4 -> 0 | P4: =100*'sku_cost_table_inbound_BK25 (2)'!P4 -> 27 | Q4: =100*'sku_cost_table_inbound_BK25 (2)'!Q4 -> 15 | R4: =100*'sku_cost_table_inbound_BK25 (2)'!R4 -> 45
A5: JPN_RICE_1 | B5: PADJPN | C5: =100*'sku_cost_table_inbound_BK25 (2)'!C5 -> 100 | D5: =100*'sku_cost_table_inbound_BK25 (2)'!D5 -> 95 | E5: =100*'sku_cost_table_inbound_BK25 (2)'!E5 -> 5 | F5: =100*'sku_cost_table_inbound_BK25 (2)'!F5 -> 0 | G5: =100*'sku_cost_table_inbound_BK25 (2)'!G5 -> 10 | H5: =100*'sku_cost_table_inbound_BK25 (2)'!H5 -> 10 | I5: =100*'sku_cost_table_inbound_BK25 (2)'!I5 -> 5 | J5: =100*'sku_cost_table_inbound_BK25 (2)'!J5 -> 0 | K5: =100*'sku_cost_table_inbound_BK25 (2)'!K5 -> 30 | L5: 0 | M5: =100*'sku_cost_table_inbound_BK25 (2)'!M5 -> 35 | N5: =100*'sku_cost_table_inbound_BK25 (2)'!N5 -> 3 | O5: =100*'sku_cost_table_inbound_BK25 (2)'!O5 -> 0 | P5: =100*'sku_cost_table_inbound_BK25 (2)'!P5 -> 27 | Q5: =100*'sku_cost_table_inbound_BK25 (2)'!Q5 -> 15 | R5: =100*'sku_cost_table_inbound_BK25 (2)'!R5 -> 45
A6: JPN_Koshihikari | B6: MOMKosihikari | C6: =100*'sku_cost_table_inbound_BK25 (2)'!C6 -> 100 | D6: =100*'sku_cost_table_inbound_BK25 (2)'!D6 -> 95 | E6: =100*'sku_cost_table_inbound_BK25 (2)'!E6 -> 5 | F6: =100*'sku_cost_table_inbound_BK25 (2)'!F6 -> 0 | G6: =100*'sku_cost_table_inbound_BK25 (2)'!G6 -> 10 | H6: =100*'sku_cost_table_inbound_BK25 (2)'!H6 -> 10 | I6: =100*'sku_cost_table_inbound_BK25 (2)'!I6 -> 5 | J6: =100*'sku_cost_table_inbound_BK25 (2)'!J6 -> 0 | K6: =100*'sku_cost_table_inbound_BK25 (2)'!K6 -> 30 | L6: 0 | M6: =100*'sku_cost_table_inbound_BK25 (2)'!M6 -> 35 | N6: =100*'sku_cost_table_inbound_BK25 (2)'!N6 -> 3 | O6: =100*'sku_cost_table_inbound_BK25 (2)'!O6 -> 0 | P6: =100*'sku_cost_table_inbound_BK25 (2)'!P6 -> 27 | Q6: =100*'sku_cost_table_inbound_BK25 (2)'!Q6 -> 15 | R6: =100*'sku_cost_table_inbound_BK25 (2)'!R6 -> 45
A7: JPN_Koshihikari | B7: PADKosihikari | C7: =100*'sku_cost_table_inbound_BK25 (2)'!C7 -> 100 | D7: =100*'sku_cost_table_inbound_BK25 (2)'!D7 -> 95 | E7: =100*'sku_cost_table_inbound_BK25 (2)'!E7 -> 5 | F7: =100*'sku_cost_table_inbound_BK25 (2)'!F7 -> 0 | G7: =100*'sku_cost_table_inbound_BK25 (2)'!G7 -> 10 | H7: =100*'sku_cost_table_inbound_BK25 (2)'!H7 -> 10 | I7: =100*'sku_cost_table_inbound_BK25 (2)'!I7 -> 5 | J7: =100*'sku_cost_table_inbound_BK25 (2)'!J7 -> 0 | K7: =100*'sku_cost_table_inbound_BK25 (2)'!K7 -> 30 | L7: 0 | M7: =100*'sku_cost_table_inbound_BK25 (2)'!M7 -> 35 | N7: =100*'sku_cost_table_inbound_BK25 (2)'!N7 -> 3 | O7: =100*'sku_cost_table_inbound_BK25 (2)'!O7 -> 0 | P7: =100*'sku_cost_table_inbound_BK25 (2)'!P7 -> 27 | Q7: =100*'sku_cost_table_inbound_BK25 (2)'!Q7 -> 15 | R7: =100*'sku_cost_table_inbound_BK25 (2)'!R7 -> 45
A8: Reserv_Rice | B8: MOMGSJP | C8: =100*'sku_cost_table_inbound_BK25 (2)'!C8 -> 100 | D8: =100*'sku_cost_table_inbound_BK25 (2)'!D8 -> 95 | E8: =100*'sku_cost_table_inbound_BK25 (2)'!E8 -> 5 | F8: =100*'sku_cost_table_inbound_BK25 (2)'!F8 -> 0 | G8: =100*'sku_cost_table_inbound_BK25 (2)'!G8 -> 10 | H8: =100*'sku_cost_table_inbound_BK25 (2)'!H8 -> 10 | I8: =100*'sku_cost_table_inbound_BK25 (2)'!I8 -> 5 | J8: =100*'sku_cost_table_inbound_BK25 (2)'!J8 -> 0 | K8: =100*'sku_cost_table_inbound_BK25 (2)'!K8 -> 30 | L8: 0 | M8: =100*'sku_cost_table_inbound_BK25 (2)'!M8 -> 35 | N8: =100*'sku_cost_table_inbound_BK25 (2)'!N8 -> 3 | O8: =100*'sku_cost_table_inbound_BK25 (2)'!O8 -> 0 | P8: =100*'sku_cost_table_inbound_BK25 (2)'!P8 -> 27 | Q8: =100*'sku_cost_table_inbound_BK25 (2)'!Q8 -> 15 | R8: =100*'sku_cost_table_inbound_BK25 (2)'!R8 -> 45
A9: Reserv_Rice | B9: PADGSJP | C9: =100*'sku_cost_table_inbound_BK25 (2)'!C9 -> 100 | D9: =100*'sku_cost_table_inbound_BK25 (2)'!D9 -> 95 | E9: =100*'sku_cost_table_inbound_BK25 (2)'!E9 -> 5 | F9: =100*'sku_cost_table_inbound_BK25 (2)'!F9 -> 0 | G9: =100*'sku_cost_table_inbound_BK25 (2)'!G9 -> 10 | H9: =100*'sku_cost_table_inbound_BK25 (2)'!H9 -> 10 | I9: =100*'sku_cost_table_inbound_BK25 (2)'!I9 -> 5 | J9: =100*'sku_cost_table_inbound_BK25 (2)'!J9 -> 0 | K9: =100*'sku_cost_table_inbound_BK25 (2)'!K9 -> 30 | L9: 0 | M9: =100*'sku_cost_table_inbound_BK25 (2)'!M9 -> 35 | N9: =100*'sku_cost_table_inbound_BK25 (2)'!N9 -> 3 | O9: =100*'sku_cost_table_inbound_BK25 (2)'!O9 -> 0 | P9: =100*'sku_cost_table_inbound_BK25 (2)'!P9 -> 27 | Q9: =100*'sku_cost_table_inbound_BK25 (2)'!Q9 -> 15 | R9: =100*'sku_cost_table_inbound_BK25 (2)'!R9 -> 45

Sheet sku_cost_table_inbound_BK25 (2)
A1: product_name | B1: node_name | C1: price_sales_shipped | D1: cost_total | E1: profit | F1: marketing_promotion | G1: sales_admin_cost | H1: SGA_total | I1: logistics_costs | J1: warehouse_cost | K1: direct_materials_costs | L1: tariff_cost | M1: purchase_total_cost | N1: prod_indirect_labor | O1: prod_indirect_others | P1: direct_labor_costs | Q1: depreciation_others | R1: manufacturing_overhead
A2: CAL_RICE_1 | B2: MOMCAL | C2: 1 | D2: 0.95 | E2: 0.05 | F2: 0 | G2: 0.1 | H2: 0.1 | I2: 0.05 | J2: 0 | K2: 0.3 | L2: 0 | M2: 0.35 | N2: 0.03 | O2: 0 | P2: 0.27 | Q2: 0.15 | R2: 0.45
A3: CAL_RICE_1 | B3: PADCAL | C3: 1 | D3: 0.95 | E3: 0.05 | F3: 0 | G3: 0.1 | H3: 0.1 | I3: 0.05 | J3: 0 | K3: 0.3 | L3: 0 | M3: 0.35 | N3: 0.03 | O3: 0 | P3: 0.27 | Q3: 0.15 | R3: 0.45
A4: JPN_RICE_1 | B4: MOMJPN | C4: 1 | D4: 0.95 | E4: 0.05 | F4: 0 | G4: 0.1 | H4: 0.1 | I4: 0.05 | J4: 0 | K4: 0.3 | L4: 0 | M4: 0.35 | N4: 0.03 | O4: 0 | P4: 0.27 | Q4: 0.15 | R4: 0.45
A5: JPN_RICE_1 | B5: PADJPN | C5: 1 | D5: 0.95 | E5: 0.05 | F5: 0 | G5: 0.1 | H5: 0.1 | I5: 0.05 | J5: 0 | K5: 0.3 | L5: 0 | M5: 0.35 | N5: 0.03 | O5: 0 | P5: 0.27 | Q5: 0.15 | R5: 0.45
A6: JPN_Koshihikari | B6: MOMKosihikari | C6: 1 | D6: 0.95 | E6: 0.05 | F6: 0 | G6: 0.1 | H6: 0.1 | I6: 0.05 | J6: 0 | K6: 0.3 | L6: 0 | M6: 0.35 | N6: 0.03 | O6: 0 | P6: 0.27 | Q6: 0.15 | R6: 0.45
A7: JPN_Koshihikari | B7: PADKosihikari | C7: 1 | D7: 0.95 | E7: 0.05 | F7: 0 | G7: 0.1 | H7: 0.1 | I7: 0.05 | J7: 0 | K7: 0.3 | L7: 0 | M7: 0.35 | N7: 0.03 | O7: 0 | P7: 0.27 | Q7: 0.15 | R7: 0.45
A8: Reserv_Rice | B8: MOMGSJP | C8: 1 | D8: 0.95 | E8: 0.05 | F8: 0 | G8: 0.1 | H8: 0.1 | I8: 0.05 | J8: 0 | K8: 0.3 | L8: 0 | M8: 0.35 | N8: 0.03 | O8: 0 | P8: 0.27 | Q8: 0.15 | R8: 0.45
A9: Reserv_Rice | B9: PADGSJP | C9: 1 | D9: 0.95 | E9: 0.05 | F9: 0 | G9: 0.1 | H9: 0.1 | I9: 0.05 | J9: 0 | K9: 0.3 | L9: 0 | M9: 0.35 | N9: 0.03 | O9: 0 | P9: 0.27 | Q9: 0.15 | R9: 0.45
